py_mrm/__init__.py
py_mrm/py_mrm.py
py_mrm-1.2.0.dist-info/METADATA
py_mrm-1.2.0.dist-info/WHEEL
py_mrm-1.2.0.dist-info/top_level.txt
py_mrm-1.2.0.dist-info/RECORD
