Metadata-Version: 2.1
Name: py-mrm
Version: 1.2.0
Summary: Functions for multiphase reactor modeling
Author: E.A.J.F. Peters
Author-email: e.a.j.f.peters@tue.nl
Requires-Dist: numpy
Requires-Dist: scipy
